fastnn/__init__.py
fastnn/client.py
fastnn/exporting.py
fastnn/nn/__init__.py
fastnn/nn/object_detection.py
fastnn/nn/question_answering.py
fastnn/nn/token_tagging.py
fastnn/processors/__init__.py
fastnn/processors/base_processing.py
fastnn/processors/cv/__init__.py
fastnn/processors/cv/object_detection.py
fastnn/processors/nlp/__init__.py
fastnn/processors/nlp/question_answering.py
fastnn/processors/nlp/token_tagging.py
fastnn/utils/__init__.py
fastnn/utils/cv.py
fastnn/utils/qa/__init__.py
fastnn/utils/qa/squad.py
fastnn/utils/qa/squad_metrics.py
fastnn-0.4.0.dist-info/LICENSE
fastnn-0.4.0.dist-info/METADATA
fastnn-0.4.0.dist-info/WHEEL
fastnn-0.4.0.dist-info/RECORD
