Metadata-Version: 2.1
Name: fastnn
Version: 0.4.0
Summary: A python library and framework for fast neural network computations.
Home-page: https://andrewchang.dev/fastnn/
License: MIT
Author: Andrew Chang
Author-email: aychang995@gmail.com
Requires-Python: >=3.9,<3.12
Classifier: License :: OSI Approved :: MIT License
Classifier: Programming Language :: Python :: 3
Classifier: Programming Language :: Python :: 3.9
Classifier: Programming Language :: Python :: 3.10
Classifier: Programming Language :: Python :: 3.11
Provides-Extra: docs
Provides-Extra: ios
Provides-Extra: jupyter
Provides-Extra: torch
Requires-Dist: accelerate (>=0.24.1,<0.25.0)
Requires-Dist: auto-gptq (>=0.4.2,<0.5.0)
Requires-Dist: coremltools (>=7.0,<8.0) ; extra == "ios"
Requires-Dist: jupyter (>=1.0.0,<2.0.0) ; extra == "jupyter"
Requires-Dist: jupyterlab (>=4.0.7,<5.0.0) ; extra == "jupyter"
Requires-Dist: matplotlib (>=3.8.0,<4.0.0) ; extra == "jupyter"
Requires-Dist: mkdocs (>=1.5.3,<2.0.0) ; extra == "docs"
Requires-Dist: mkdocs-material (>=9.4.7,<10.0.0) ; extra == "docs"
Requires-Dist: mkdocstrings (>=0.18.0,<0.19.0) ; extra == "docs"
Requires-Dist: optimum (>=1.13.2,<2.0.0)
Requires-Dist: sentence-transformers (>=2.2.2,<3.0.0)
Requires-Dist: torch (==2.0.0) ; extra == "torch"
Requires-Dist: torchaudio (==2.*)
Requires-Dist: torchvision (==0.*) ; extra == "torch"
Requires-Dist: transformers (>=4.34.1,<5.0.0)
Requires-Dist: tritonclient[all] (>=2.39.0,<3.0.0)
Requires-Dist: wget (>=3.2,<4.0)
Project-URL: Documentation, https://andrewchang.dev/fastnn/
Project-URL: Repository, https://github.com/aychang95/fastnn
